automox_console_sdk/__init__.py
automox_console_sdk/api_client.py
automox_console_sdk/configuration.py
automox_console_sdk/rest.py
automox_console_sdk/api/__init__.py
automox_console_sdk/api/api_keys_api.py
automox_console_sdk/api/approvals_api.py
automox_console_sdk/api/commands_api.py
automox_console_sdk/api/devices_api.py
automox_console_sdk/api/events_api.py
automox_console_sdk/api/extracts_api.py
automox_console_sdk/api/groups_api.py
automox_console_sdk/api/organizations_api.py
automox_console_sdk/api/packages_api.py
automox_console_sdk/api/policies_api.py
automox_console_sdk/api/reports_api.py
automox_console_sdk/api/users_api.py
automox_console_sdk/api/worklets_api.py
automox_console_sdk/models/__init__.py
automox_console_sdk/models/any_ofinline_response2001.py
automox_console_sdk/models/api_key.py
automox_console_sdk/models/api_key_user.py
automox_console_sdk/models/api_keys_id_body.py
automox_console_sdk/models/approvals_id_body.py
automox_console_sdk/models/batch.py
automox_console_sdk/models/command.py
automox_console_sdk/models/compatibility_checks.py
automox_console_sdk/models/custom_policy.py
automox_console_sdk/models/custom_policy_configuration.py
automox_console_sdk/models/data_extract.py
automox_console_sdk/models/data_extract_parameters.py
automox_console_sdk/models/dataextracts_body.py
automox_console_sdk/models/dataextracts_parameters.py
automox_console_sdk/models/device_filters.py
automox_console_sdk/models/device_filters_inner.py
automox_console_sdk/models/device_status.py
automox_console_sdk/models/device_status_policy_statuses.py
automox_console_sdk/models/event.py
automox_console_sdk/models/event_data.py
automox_console_sdk/models/filters.py
automox_console_sdk/models/id_files_body.py
automox_console_sdk/models/id_queues_body.py
automox_console_sdk/models/inline_response200.py
automox_console_sdk/models/inline_response2001.py
automox_console_sdk/models/inline_response2002.py
automox_console_sdk/models/inline_response2003.py
automox_console_sdk-0.3.0.dist-info/LICENSE
automox_console_sdk-0.3.0.dist-info/METADATA
automox_console_sdk-0.3.0.dist-info/WHEEL
automox_console_sdk-0.3.0.dist-info/top_level.txt
automox_console_sdk-0.3.0.dist-info/RECORD
