Metadata-Version: 2.1
Name: automox-console-sdk
Version: 0.3.0
Summary: Automox Console SDK for Python
Home-page: https://github.com/AutomoxCommunity/automox-console-sdk-python
Author-email: support@automox.com
License: MIT
Keywords: Swagger,Automox Console API
Platform: UNKNOWN
Classifier: Intended Audience :: Developers
Classifier: Natural Language :: English
Classifier: License :: OSI Approved :: MIT License
Classifier: Programming Language :: Python
Classifier: Programming Language :: Python :: 3
Classifier: Programming Language :: Python :: 3.9
License-File: LICENSE
Requires-Dist: urllib3 (>=1.15)
Requires-Dist: six (>=1.10)
Requires-Dist: certifi
Requires-Dist: python-dateutil
